conv_anal/__init__.py
conv_anal/__main__.py
conv_anal/chatgpt_embeddings.py
conv_anal/chatgpt_graph.py
conv_anal/chatgpt_memory.py
conv_anal/code_exec.py
conv_anal/gentera.py
conv_anal/gnp_single.py
conv_anal/gnp_vectorize_collection.py
conv_anal/infer_data.py
conv_anal/interactive.py
conv_anal/langchain_rag.py
conv_anal/time_series.py
conv_anal/data/gentera/gentera.csv
conv_anal/data/gentera/gentera_schema.csv
conv_anal/data/gentera/gentera_schema_meanings.csv
conv_anal/gnp_collection/Dotal_GNP.py
conv_anal/gnp_collection/Platino_GNP.py
conv_anal/gnp_collection/Privilegio_GNP.py
conv_anal/gnp_collection/Profesional_GNP.py
conv_anal/gnp_collection/Trasciende_GNP.py
conv_anal/gnp_collection/VisionPlus_GNP.py
conv_anal/gnp_collection/__init__.py
conv_anal/gnp_collection/collection_prompt.py
qualtop_conversational_analysis-0.33.dist-info/METADATA
qualtop_conversational_analysis-0.33.dist-info/WHEEL
qualtop_conversational_analysis-0.33.dist-info/top_level.txt
qualtop_conversational_analysis-0.33.dist-info/RECORD
